<?xml version="1.0" encoding="UTF-8"?>
<manifest>

  <!-- System -->
  <remove-project name="platform/build"/>
  <remove-project name="platform/build/soong"/>
  <remove-project name="platform/frameworks/base"/>
  <remove-project name="platform/packages/apps/Settings"/>
  <remove-project name="platform/packages/providers/DownloadProvider"/>
  <remove-project name="platform/system/core"/>
  <remove-project name="platform/system/logging"/>

  <!-- Devices -->
  <remove-project name="device/amlogic/yukawa"/>
  <remove-project name="device/amlogic/yukawa-kernel"/>
  <remove-project name="device/google/atv"/>
  <remove-project name="device/google/barbet"/>
  <remove-project name="device/google/barbet-sepolicy"/>
  <remove-project name="device/google/bluejay"/>
  <remove-project name="device/google/bluejay-kernel"/>
  <remove-project name="device/google/bluejay-sepolicy"/>
  <remove-project name="device/google/bramble"/>
  <remove-project name="device/google/bramble-sepolicy"/>
  <remove-project name="device/google/coral"/>
  <remove-project name="device/google/coral-kernel"/>
  <remove-project name="device/google/coral-sepolicy"/>
  <remove-project name="device/google/gs101"/>
  <remove-project name="device/google/gs101-sepolicy"/>
  <remove-project name="device/google/redbull"/>
  <remove-project name="device/google/redbull-kernel"/>
  <remove-project name="device/google/redbull-sepolicy"/>
  <remove-project name="device/google/redfin"/>
  <remove-project name="device/google/redfin-sepolicy"/>
  <remove-project name="device/google/sunfish"/>
  <remove-project name="device/google/sunfish-kernel"/>
  <remove-project name="device/google/sunfish-sepolicy"/>
  <remove-project name="device/google/trout"/>
  <remove-project name="device/google_car"/>
  <remove-project name="device/linaro/dragonboard"/>
  <remove-project name="device/linaro/dragonboard-kernel"/>
  <remove-project name="device/linaro/hikey"/>
  <remove-project name="device/linaro/hikey-kernel"/>
  <remove-project name="device/linaro/poplar"/>
  <remove-project name="device/linaro/poplar-kernel"/>
  <remove-project name="device/mediatek/wembley-sepolicy"/>
  <remove-project name="device/ti/beagle-x15"/>
  <remove-project name="device/ti/beagle-x15-kernel"/>

  <!-- Prebuilts -->
  <remove-project name="platform/prebuilts/go/linux-x86"/>
  <remove-project name="platform/prebuilts/jdk/jdk17"/>
  <remove-project name="platform/prebuilts/r8"/>

  <!-- Clang (and repos with fixes) -->
  <remove-project name="platform/packages/modules/Connectivity"/>
  <remove-project name="platform/prebuilts/clang-tools"/>
  <remove-project name="platform/prebuilts/clang/host/linux-x86"/>

  <!-- Darwin prebuilts -->
  <remove-project name="platform/prebuilts/bazel/darwin-x86_64"/>
  <remove-project name="platform/prebuilts/clang/host/darwin-x86"/>
  <remove-project name="platform/prebuilts/go/darwin-x86"/>

</manifest>
